source/__init__.py
source/scl.py
sathyabama_updates-0.1.dist-info/Licence
sathyabama_updates-0.1.dist-info/METADATA
sathyabama_updates-0.1.dist-info/WHEEL
sathyabama_updates-0.1.dist-info/entry_points.txt
sathyabama_updates-0.1.dist-info/top_level.txt
sathyabama_updates-0.1.dist-info/RECORD
