Metadata-Version: 2.1
Name: sathyabama-updates
Version: 0.1
Summary: Fetches latest updates of news and events and Pretty prints it on terminal.
Home-page: https://github.com/manojtummala/ucl
Author: Manoj Tummala
Author-email: tummalamanoj2002@gmail.com
License: UNKNOWN
Platform: UNKNOWN
Classifier: Programming Language :: Python :: 3
Classifier: License :: OSI Approved :: MIT License
Classifier: Operating System :: OS Independent
Requires-Dist: Click
Requires-Dist: requests
Requires-Dist: tabulate
